standard_e2e/__init__.py
standard_e2e/constants.py
standard_e2e/enums.py
standard_e2e/unified_dataset.py
standard_e2e/caching/__init__.py
standard_e2e/caching/process_source_dataset.py
standard_e2e/caching/source_dataset_converter.py
standard_e2e/caching/source_dataset_processor.py
standard_e2e/caching/adapters/__init__.py
standard_e2e/caching/adapters/abstract_adapter.py
standard_e2e/caching/adapters/identity_adapters.py
standard_e2e/caching/adapters/pano_adapter.py
standard_e2e/caching/segment_context/__init__.py
standard_e2e/caching/segment_context/future_detections.py
standard_e2e/caching/segment_context/future_past_states_from_matrices.py
standard_e2e/caching/segment_context/segment_context_aggregator.py
standard_e2e/caching/src_datasets/__init__.py
standard_e2e/caching/src_datasets/waymo_e2e/__init__.py
standard_e2e/caching/src_datasets/waymo_e2e/waymo_e2e_dataset_converter.py
standard_e2e/caching/src_datasets/waymo_e2e/waymo_e2e_dataset_processor.py
standard_e2e/caching/src_datasets/waymo_perception/__init__.py
standard_e2e/caching/src_datasets/waymo_perception/waymo_perception_dataset_converter.py
standard_e2e/caching/src_datasets/waymo_perception/waymo_perception_dataset_processor.py
standard_e2e/data_structures/__init__.py
standard_e2e/data_structures/containers.py
standard_e2e/data_structures/frame_data.py
standard_e2e/data_structures/trajectory_data.py
standard_e2e/dataset_utils/__init__.py
standard_e2e/dataset_utils/frame_loader.py
standard_e2e/dataset_utils/augmentation/__init__.py
standard_e2e/dataset_utils/augmentation/augmentation.py
standard_e2e/dataset_utils/augmentation/multiple_frames_image_augmentation.py
standard_e2e/dataset_utils/augmentation/trajectory_resampling.py
standard_e2e/dataset_utils/modality_defaults/__init__.py
standard_e2e/dataset_utils/modality_defaults/modality_defaults.py
standard_e2e/dataset_utils/selector/__init__.py
standard_e2e/dataset_utils/selector/closest_timestamp_selector.py
standard_e2e-0.0.2.dist-info/licenses/LICENSE
standard_e2e-0.0.2.dist-info/METADATA
standard_e2e-0.0.2.dist-info/WHEEL
standard_e2e-0.0.2.dist-info/top_level.txt
standard_e2e-0.0.2.dist-info/RECORD
