Metadata-Version: 2.4
Name: standard_e2e
Version: 0.0.2
Summary: A unified framework for autonomous driving dataset management for end-to-end model development
Author: Stepan Konev
License: MIT
Project-URL: Homepage, https://github.com/stepankonev/StandardE2E
Project-URL: Repository, https://github.com/stepankonev/StandardE2E.git
Project-URL: Issues, https://github.com/stepankonev/StandardE2E/issues
Keywords: autonomous-driving,computer-vision,deep-learning,pytorch,dataset-management,end-to-end
Classifier: Development Status :: 4 - Beta
Classifier: Intended Audience :: Developers
Classifier: Intended Audience :: Science/Research
Classifier: License :: OSI Approved :: MIT License
Classifier: Operating System :: OS Independent
Classifier: Programming Language :: Python :: 3
Classifier: Programming Language :: Python :: 3.11
Classifier: Programming Language :: Python :: 3.12
Classifier: Topic :: Software Development :: Libraries :: Python Modules
Classifier: Topic :: Scientific/Engineering :: Artificial Intelligence
Classifier: Topic :: Scientific/Engineering :: Image Processing
Requires-Python: <3.14,>=3.11
License-File: LICENSE
Requires-Dist: torch
Requires-Dist: pandas
Requires-Dist: pyarrow
Requires-Dist: Pillow
Requires-Dist: albumentations
Requires-Dist: pyyaml
Requires-Dist: tensorflow-cpu
Requires-Dist: tqdm
Requires-Dist: pydantic<3,>=2.6
Provides-Extra: dev
Requires-Dist: pytest>=7.0.0; extra == "dev"
Requires-Dist: pytest-cov>=4.0.0; extra == "dev"
Requires-Dist: pytest-xdist>=3.0.0; extra == "dev"
Requires-Dist: black>=23.0.0; extra == "dev"
Requires-Dist: isort>=5.12.0; extra == "dev"
Requires-Dist: flake8>=6.0.0; extra == "dev"
Requires-Dist: mypy>=1.0.0; extra == "dev"
Requires-Dist: lark; extra == "dev"
Requires-Dist: pandas-stubs>=2.2.0.240909; extra == "dev"
Requires-Dist: types-PyYAML; extra == "dev"
Requires-Dist: types-tqdm; extra == "dev"
Requires-Dist: types-tensorflow; extra == "dev"
Requires-Dist: matplotlib; extra == "dev"
Provides-Extra: test
Requires-Dist: pytest>=7.0.0; extra == "test"
Requires-Dist: pytest-cov>=4.0.0; extra == "test"
Requires-Dist: pytest-xdist>=3.0.0; extra == "test"
Provides-Extra: lint
Requires-Dist: black>=23.0.0; extra == "lint"
Requires-Dist: isort>=5.12.0; extra == "lint"
Requires-Dist: flake8>=6.0.0; extra == "lint"
Requires-Dist: mypy>=1.0.0; extra == "lint"
Requires-Dist: pandas-stubs>=2.2.0.240909; extra == "lint"
Requires-Dist: types-PyYAML; extra == "lint"
Requires-Dist: types-tqdm; extra == "lint"
Requires-Dist: types-tensorflow; extra == "lint"
Dynamic: license-file
